AUTHORS
COPYING
MANIFEST.in
README
setup.py
electrode/__init__.py
electrode/cexpressions.pyx
electrode/colors.py
electrode/constraints.py
electrode/electrode.py
electrode/expressions.py
electrode/pattern_constraints.py
electrode/polygons.py
electrode/saddle.py
electrode/system.py
electrode/transformations.c
electrode/transformations.py
electrode/utils.py
electrode/xic.py
electrode.egg-info/PKG-INFO
electrode.egg-info/SOURCES.txt
electrode.egg-info/dependency_links.txt
electrode.egg-info/namespace_packages.txt
electrode.egg-info/requires.txt
electrode.egg-info/top_level.txt
electrode/tests/__init__.py
electrode/tests/test_electrode.py
electrode/tests/test_polygons.py
electrode/tests/test_traps.py
electrode/tests/test_utils.py
notebooks/rfjunction.ipynb
notebooks/rfjunction.py
notebooks/threefold.ipynb
notebooks/threefold.py