Metadata-Version: 1.0
Name: electrode
Version: 1.4
Summary: toolkit to develop and analyze rf surface ion traps
Home-page: http://launchpad.net/electrode
Author: Robert Jordens
Author-email: jordens@gmail.com
License: GPLv3+
Platform: UNKNOWN
